MANIFEST.in
README.rst
ez_setup.py
platform_setup.py
setup.cfg
setup.py
hwiopy/__init__.py
hwiopy.egg-info/PKG-INFO
hwiopy.egg-info/SOURCES.txt
hwiopy.egg-info/dependency_links.txt
hwiopy.egg-info/top_level.txt
hwiopy/core/__init__.py
hwiopy/core/core.py
hwiopy/maps/bbb_sysmap.json
hwiopy/maps/cortexA8_memmap.json
hwiopy/maps/cortexA8_registers.json
hwiopy/maps/sitara_termmodes.json
hwiopy/overlays/bbb_template_gpio.dts
hwiopy/overlays/test.dts
hwiopy/platforms/__init__.py
hwiopy/platforms/beagle.py
hwiopy/setup_utils/bbb_dtc.sh
hwiopy/systems/__init__.py
hwiopy/systems/cortexA8.py